wixio/__init__.py
wixio/algo.py
wixio/baseio.py
wixio/format.py
wixio/image.py
wixio/logger.py
wixio/metrics.py
wixio/ops.py
wixio/sys.py
wixio/time.py
wixio/crawl/__init__.py
wixio/retry/__init__.py
wixio/retry/retry.py
wixio/retry/retry_compat.py
wixio-0.0.2.dist-info/LICENSE
wixio-0.0.2.dist-info/METADATA
wixio-0.0.2.dist-info/WHEEL
wixio-0.0.2.dist-info/top_level.txt
wixio-0.0.2.dist-info/RECORD
