Metadata-Version: 2.1
Name: wixio
Version: 0.0.2
Summary: A Wide x file IO utility library for Python.
Author-email: Jiawei Li <Li.J.W.adrian421@hotmail.com>
License: The MIT License (MIT)
Project-URL: Source, https://github.com/adrianJW421/wixio
Project-URL: Tracker, https://github.com/adrianJW421/wixio/issues
Keywords: io,file,tools
Classifier: Programming Language :: Python :: 3
Classifier: License :: OSI Approved :: MIT License
Classifier: Operating System :: OS Independent
License-File: LICENSE
